Metadata-Version: 2.1
Name: gruut-lang-nl
Version: 2.0.2
Summary: Dutch language files for gruut tokenizer/phonemizer
Home-page: https://github.com/rhasspy/gruut
Author: Michael Hansen
Author-email: mike@rhasspy.org
License: UNKNOWN
Platform: UNKNOWN
Classifier: Programming Language :: Python :: 3
Classifier: License :: OSI Approved :: MIT License
